<?xml version="1.0"?>
<!DOCTYPE hibernate-mapping PUBLIC
"-//Hibernate/Hibernate Mapping DTD 3.0//EN"
"http://www.hibernate.org/dtd/hibernate-mapping-3.0.dtd">

<hibernate-mapping package="cn.edu.tju.scs.domain">

<class name="Admin" table="admin">
    <id name="adminId" type="java.lang.Integer">
        <!--  //字段自增-->
        <generator class="native"/>
    </id>

    <property name="adminName" type="java.lang.String"  not-null="true"/>
    <property name="password" type="java.lang.String"  not-null="true"/>
    <property name="createtime" type="java.sql.Timestamp" not-null="false"/>
    <property name="updatetime" type="java.sql.Timestamp" not-null="false"/>

</class>

</hibernate-mapping>